nhk/genre.py
nhk/service.py
nhk/area.py
nhk/__init__.py
nhk/util.py
nhk/client.py
nhk_api-0.0.2.dist-info/top_level.txt
nhk_api-0.0.2.dist-info/RECORD
nhk_api-0.0.2.dist-info/entry_points.txt
nhk_api-0.0.2.dist-info/METADATA
nhk_api-0.0.2.dist-info/WHEEL
nhk_api-0.0.2.dist-info/pydist.json
nhk_api-0.0.2.dist-info/DESCRIPTION.rst
