Metadata-Version: 2.0
Name: nhk-api
Version: 0.0.2
Summary: Python client for NHK API
Home-page: https://github.com/drillbits/nhk-api
Author: Jiro Nejime
Author-email: neji@drillbits.jp
License: MIT License
Platform: UNKNOWN
Classifier: Development Status :: 2 - Pre-Alpha
Classifier: Intended Audience :: Developers
Classifier: License :: OSI Approved :: MIT License
Classifier: Programming Language :: Python
Classifier: Programming Language :: Python :: 3.3
Requires-Dist: requests
Provides-Extra: testing
Requires-Dist: testfixtures; extra == 'testing'
